<annotation>
	<folder>Kiwi</folder>
	<filename>IMG_20200503_143958.jpg</filename>
	<path>/Users/aliyarajwani/Documents/Repos/Object Recognition Chowtime/images/aliya_train/Kiwi/IMG_20200503_143958.jpg</path>
	<source>
		<database>Unknown</database>
	</source>
	<size>
		<width>800</width>
		<height>600</height>
		<depth>3</depth>
	</size>
	<segmented>0</segmented>
	<object>
		<name>kiwi</name>
		<pose>Unspecified</pose>
		<truncated>0</truncated>
		<difficult>0</difficult>
		<bndbox>
			<xmin>380</xmin>
			<ymin>44</ymin>
			<xmax>607</xmax>
			<ymax>341</ymax>
		</bndbox>
	</object>
</annotation>
